Metadata-Version: 1.0
Name: udacity-probability-distributions
Version: 0.1
Summary: Gaussian and Binomial distributions
Home-page: UNKNOWN
Author: Ravi Bansal
Author-email: UNKNOWN
License: UNKNOWN
Platform: UNKNOWN
